ark_sdk_test/__init__.py
ark_sdk_test/client.py
ark_sdk_test/image_generation.py
ark_sdk_test/sdk.py
ark_sdk_test/text_generation.py
ark_sdk_test/video_generation.py
ark_sdk_test-1.0.1.dist-info/licenses/LICENSE
ark_sdk_test-1.0.1.dist-info/METADATA
ark_sdk_test-1.0.1.dist-info/WHEEL
ark_sdk_test-1.0.1.dist-info/top_level.txt
ark_sdk_test-1.0.1.dist-info/RECORD
